nonebot/adapters/yunhu/__init__.py
nonebot/adapters/yunhu/adapter.py
nonebot/adapters/yunhu/bot.py
nonebot/adapters/yunhu/config.py
nonebot/adapters/yunhu/event.py
nonebot/adapters/yunhu/exception.py
nonebot/adapters/yunhu/message.py
nonebot/adapters/yunhu/models/__init__.py
nonebot/adapters/yunhu/models/api.py
nonebot/adapters/yunhu/models/common.py
nonebot/adapters/yunhu/permission.py
nonebot/adapters/yunhu/tool.py
nonebot_adapter_yunhu-0.1.6.dist-info/METADATA
nonebot_adapter_yunhu-0.1.6.dist-info/WHEEL
nonebot_adapter_yunhu-0.1.6.dist-info/licenses/LICENSE
nonebot_adapter_yunhu-0.1.6.dist-info/RECORD
